ltf/__init__.py
ltf/cli/__init__.py
ltf/cli/cli.py
ltf/cli/validate.py
ltf/config.py
ltf/data/prompt.yaml
ltf/language_transfer_flashcards.py
ltf/models.py
ltf/utils.py
ltf/youtube_transcript.py
language_transfer_flashcards-0.1.4.dist-info/entry_points.txt
language_transfer_flashcards-0.1.4.dist-info/LICENSE
language_transfer_flashcards-0.1.4.dist-info/METADATA
language_transfer_flashcards-0.1.4.dist-info/WHEEL
language_transfer_flashcards-0.1.4.dist-info/RECORD
