Metadata-Version: 2.1
Name: language-transfer-flashcards
Version: 0.1.4
Summary: CLI tool converting Language Transfer lessons into Anki flashcards, automating content extraction for efficient language learning.
Home-page: https://github.com/t-charura/language-transfer-flashcards
License: MIT
Author: Tendai
Author-email: tendai.charura@gmail.com
Requires-Python: >=3.11,<3.14
Classifier: License :: OSI Approved :: MIT License
Classifier: Programming Language :: Python :: 3
Classifier: Programming Language :: Python :: 3.11
Classifier: Programming Language :: Python :: 3.12
Requires-Dist: langchain-community (>=0.3.0,<0.4.0)
Requires-Dist: langchain-openai (>=0.3.0,<0.4.0)
Requires-Dist: pydantic-settings (>=2.4.0,<3.0.0)
Requires-Dist: pytube (>=15.0.0,<16.0.0)
Requires-Dist: rich (>=13.7.1,<14.0.0)
Requires-Dist: typer (>=0.15.0,<0.16.0)
Requires-Dist: youtube-transcript-api (>=1.1.0,<2.0.0)
